ariel/__init__.py
ariel_client_triton-0.1.2.dist-info/LICENSE
ariel_client_triton-0.1.2.dist-info/WHEEL
ariel_client_triton-0.1.2.dist-info/METADATA
ariel_client_triton-0.1.2.dist-info/RECORD
