Metadata-Version: 2.1
Name: ariel-client-triton
Version: 0.1.2
Summary: Client utilities for the triton inference server
Author: Luis Vega
Author-email: vegaluisjose@gmail.com
Requires-Python: >=3.7
Classifier: Programming Language :: Python :: 3
Classifier: Programming Language :: Python :: 3.10
Classifier: Programming Language :: Python :: 3.7
Classifier: Programming Language :: Python :: 3.8
Classifier: Programming Language :: Python :: 3.9
Requires-Dist: grpcio (>=1.41.0,<1.42.0)
Requires-Dist: tritonclient[all] (>=2.22.0,<3.0.0)
